aiotica/__init__.py
aiotica/event_receiver.py
aiotica/iot_access_control.py
aiotica/model/__init__.py
aiotica/model/ack.py
aiotica/model/command.py
aiotica/model/control_config.py
aiotica/model/error_log.py
aiotica/model/iot_credentials.py
aiotica/model/log_base.py
aiotica/model/mqtt_message.py
aiotica/model/sensor_value.py
aiotica/model/thing_config.py
aiotica/platform_specific/__init__.py
aiotica/platform_specific/greengrass_client.py
aiotica/platform_specific/mqtt_base_interface.py
aiotica/platform_specific/paho_mqtt_client.py
aiotica/service/__init__.py
aiotica/service/api_service.py
aiotica/service/config.py
aiotica-1.0.15.dist-info/METADATA
aiotica-1.0.15.dist-info/WHEEL
aiotica-1.0.15.dist-info/top_level.txt
aiotica-1.0.15.dist-info/RECORD
