Metadata-Version: 2.1
Name: aiotica
Version: 1.0.15
Summary: Gateway programming library of KASO AioTica
Home-page: 
Author: KASO
Classifier: Programming Language :: Python :: 3
Classifier: License :: OSI Approved :: MIT License
Classifier: Operating System :: OS Independent
Requires-Python: >=3.8
Requires-Dist: Rx ==3.2.0
Requires-Dist: paho-mqtt ==2.1.0
Requires-Dist: boto3 ==1.33.13
Requires-Dist: awsiotsdk ==1.21.4
Requires-Dist: requests ==2.31.0
